LICENSE
MANIFEST.in
README.md
requirements.txt
setup.cfg
setup.py
ipyparallel_mesos/__init__.py
ipyparallel_mesos/launcher.py
ipyparallel_mesos.egg-info/PKG-INFO
ipyparallel_mesos.egg-info/SOURCES.txt
ipyparallel_mesos.egg-info/dependency_links.txt
ipyparallel_mesos.egg-info/requires.txt
ipyparallel_mesos.egg-info/top_level.txt