Metadata-Version: 1.0
Name: ipyparallel-mesos
Version: 0.0.2
Summary: ipyparallel launchers for mesos using docker and marathon
Home-page: https://github.com/ActivisionGameScience/ipyparallel-mesos/
Author: John Dennison
Author-email: john.dennison@activision.com
License: UNKNOWN
Platform: UNKNOWN
